norc/__init__.py
norc/analysis_ui.py
norc/classes/__init__.py
norc/classes/application_state.py
norc/core/__init__.py
norc/core/analyze.py
norc/core/generate_test_data.py
norc/core/plot_rel_dev.py
norc/core/plotmanager.py
norc/core/score.py
norc/helpers/__init__.py
norc/helpers/util.py
norc/ui/__init__.py
norc/ui/chart.py
norc/ui/dimension_picker.py
norc/ui/dimension_picker.ui
norc/ui/examine_tab.py
norc/ui/examine_tab.ui
norc/ui/mainwindow.py
norc/ui/mainwindow.ui
norc/ui/qt_utils.py
norc/ui/ratings_tab.py
norc/ui/ratings_tab.ui
norc/ui/score_table.py
norc/ui/ui_util.py
norc-0.0.1.dist-info/METADATA
norc-0.0.1.dist-info/WHEEL
norc-0.0.1.dist-info/entry_points.txt
norc-0.0.1.dist-info/top_level.txt
norc-0.0.1.dist-info/RECORD
