Metadata-Version: 2.4
Name: norc
Version: 0.0.1
Summary: Noise Resilient Hardware Counters in HPC
Author-email: Lukas Fuchs <lukas.fuchs@stud.tu-darmstadt.de>, Ahmad Tarraf <ahmad.tarraf@tu-darmstadt.de>, Alexander Geiß <alexander.geiss1@tu-darmstadt.de>
Maintainer-email: Lukas Fuchs <lukas.fuchs@stud.tu-darmstadt.de>, Ahmad Tarraf <ahmad.tarraf@tu-darmstadt.de>, Alexander Geiß <alexander.geiss1@tu-darmstadt.de>
Project-URL: Homepage, https://github.com/tuda-parallel/NORC
Project-URL: Documentation, https://github.com/tuda-parallel/NORC/docs
Project-URL: Repository, https://github.com/tuda-parallel/NORC
Project-URL: Bug Tracker, https://github.com/tuda-parallel/NORC/issues
Project-URL: Changelog, https://github.com/tuda-parallel/NORC/blob/master/CHANGELOG.md
Keywords: hardware counter,noise,HPC
Classifier: Development Status :: 5 - Production/Stable
Classifier: License :: OSI Approved :: BSD License
Classifier: Operating System :: OS Independent
Classifier: Programming Language :: Python :: 3
Classifier: Programming Language :: Python :: 3 :: Only
Classifier: Programming Language :: Python :: 3.8
Classifier: Programming Language :: Python :: 3.9
Classifier: Programming Language :: Python :: 3.10
Classifier: Programming Language :: Python :: 3.11
Classifier: Programming Language :: Python :: 3.12
Classifier: Programming Language :: Python :: 3.13
Classifier: Operating System :: OS Independent
Classifier: Intended Audience :: Developers
Classifier: Intended Audience :: Science/Research
Classifier: Topic :: Scientific/Engineering
Classifier: Topic :: Software Development
Classifier: Topic :: Software Development :: Libraries :: Python Modules
Requires-Python: >=3.8
Requires-Dist: numpy~=1.24
Requires-Dist: matplotlib~=3.7
Requires-Dist: PySide6~=6.6
Requires-Dist: termcolor~=2.4.0
Requires-Dist: pycubexr~=2.0.1
Requires-Dist: tqdm~=4.67
Provides-Extra: development-libs
Requires-Dist: black; extra == "development-libs"
Requires-Dist: isort; extra == "development-libs"
Requires-Dist: nbstripout; extra == "development-libs"
